pybase24/__init__.py
pybase24/base24.py
pybase24-1.0.0.dist-info/LICENSE
pybase24-1.0.0.dist-info/METADATA
pybase24-1.0.0.dist-info/WHEEL
pybase24-1.0.0.dist-info/top_level.txt
pybase24-1.0.0.dist-info/RECORD
