Metadata-Version: 2.1
Name: pybase24
Version: 1.0.0
Summary: Encoder and decoder for the Base24 encoding.
Home-page: https://github.com/mildmelon/pybase24
Author: Caidan Williams
Author-email: caidanstevenwilliams@gmail.com
License: UNKNOWN
Platform: UNKNOWN
Classifier: Programming Language :: Python :: 3
Classifier: License :: OSI Approved :: MIT License
Classifier: Operating System :: OS Independent
Requires-Python: >=3.6
